compmec/shape/__init__.py
compmec/shape/curve.py
compmec/shape/jordancurve.py
compmec/shape/plot.py
compmec/shape/polygon.py
compmec/shape/primitive.py
compmec/shape/shape.py
compmec_shape-1.0.2.dist-info/LICENSE.md
compmec_shape-1.0.2.dist-info/METADATA
compmec_shape-1.0.2.dist-info/WHEEL
compmec_shape-1.0.2.dist-info/RECORD
