Metadata-Version: 2.1
Name: compmec-shape
Version: 1.0.2
Summary: Geometric 2D library
Author: Carlos Adir
Author-email: carlos.adir.leite@gmail.com
Requires-Python: >=3.7,<4.0
Classifier: Programming Language :: Python :: 3
Classifier: Programming Language :: Python :: 3.7
Classifier: Programming Language :: Python :: 3.8
Classifier: Programming Language :: Python :: 3.9
Classifier: Programming Language :: Python :: 3.10
Classifier: Programming Language :: Python :: 3.11
Requires-Dist: compmec-nurbs (>=1.0.7,<2.0.0)
Requires-Dist: matplotlib (>=3.4.0,<4.0.0)
Requires-Dist: numpy (>=1.0.0,<2.0.0)
